Workbook
Name Slicer_City: #N/A
Name Slicer_Year: #N/A

Sheet Clean Dataset
A1: Date | B1: City | C1: Rep | D1: Store | E1: Prod | F1: Cost | G1: Sale | H1: Profit | I1: Margin % | J1: Year | K1: Month | L1: Day | M1: month name
A2: 38634 | B2: Jubail | C2: Yahia | D2: Othaim | E2: Toys | F2: 373.66 | G2: 498.22 | H2: =Table1[[#This Row],[Sale]]-Table1[[#This Row],[Cost]] -> 124.56 | I2: =Table1[[#This Row],[Profit]]/Table1[[#This Row],[Sale]] -> 0.25001004 | J2: =YEAR(A:A) -> 2005 | K2: =MONTH(Table1[[#This Row],[Date]]) -> 10 | L2: =DAY(Table1[[#This Row],[Date]]) -> 9 | M2: =CHOOSE(K2,"Jan", "Feb", "Mar", "Apr", "May", "Jun", "Jul", "Aug", "Sep", "Oct", "Nov", "Dec") -> Oct
A3: 38653 | B3: Abha | C3: Yahia | D3: Panda | E3: Toys | F3: 2714.01 | G3: 4600.01 | H3: =Table1[[#This Row],[Sale]]-Table1[[#This Row],[Cost]] -> 1886 | I3: =Table1[[#This Row],[Profit]]/Table1[[#This Row],[Sale]] -> 0.40999911 | J3: =YEAR(A:A) -> 2005 | K3: =MONTH(Table1[[#This Row],[Date]]) -> 10 | L3: =DAY(Table1[[#This Row],[Date]]) -> 28 | M3: =CHOOSE(K3,"Jan", "Feb", "Mar", "Apr", "May", "Jun", "Jul", "Aug", "Sep", "Oct", "Nov", "Dec") -> Oct
A4: 38766 | B4: Riyadh | C4: Mjeed | D4: Lulu | E4: Home | F4: 3718.96 | G4: 4958.62 | H4: =Table1[[#This Row],[Sale]]-Table1[[#This Row],[Cost]] -> 1239.66 | I4: =Table1[[#This Row],[Profit]]/Table1[[#This Row],[Sale]] -> 0.25000101 | J4: =YEAR(A:A) -> 2006 | K4: =MONTH(Table1[[#This Row],[Date]]) -> 2 | L4: =DAY(Table1[[#This Row],[Date]]) -> 18 | M4: =CHOOSE(K4,"Jan", "Feb", "Mar", "Apr", "May", "Jun", "Jul", "Aug", "Sep", "Oct", "Nov", "Dec") -> Feb
A5: 38718 | B5: Jubail | C5: Yahia | D5: Panda | E5: Home | F5: 2791.45 | G5: 4731.27 | H5: =Table1[[#This Row],[Sale]]-Table1[[#This Row],[Cost]] -> 1939.82 | I5: =Table1[[#This Row],[Profit]]/Table1[[#This Row],[Sale]] -> 0.40999985 | J5: =YEAR(A:A) -> 2006 | K5: =MONTH(Table1[[#This Row],[Date]]) -> 1 | L5: =DAY(Table1[[#This Row],[Date]]) -> 1 | M5: =CHOOSE(K5,"Jan", "Feb", "Mar", "Apr", "May", "Jun", "Jul", "Aug", "Sep", "Oct", "Nov", "Dec") -> Jan
A6: 38381 | B6: Jeddah | C6: Mjeed | D6: Panda | E6: Home | F6: 2929.76 | G6: 272.62 | H6: =Table1[[#This Row],[Sale]]-Table1[[#This Row],[Cost]] -> -2657.14 | I6: =Table1[[#This Row],[Profit]]/Table1[[#This Row],[Sale]] -> -9.7466804 | J6: =YEAR(A:A) -> 2005 | K6: =MONTH(Table1[[#This Row],[Date]]) -> 1 | L6: =DAY(Table1[[#This Row],[Date]]) -> 29 | M6: =CHOOSE(K6,"Jan", "Feb", "Mar", "Apr", "May", "Jun", "Jul", "Aug", "Sep", "Oct", "Nov", "Dec") -> Jan
A7: 38364 | B7: Dammam | C7: Abdul | D7: Othaim | E7: Food | F7: 3276.93 | G7: 7346.45 | H7: =Table1[[#This Row],[Sale]]-Table1[[#This Row],[Cost]] -> 4069.52 | I7: =Table1[[#This Row],[Profit]]/Table1[[#This Row],[Sale]] -> 0.55394374 | J7: =YEAR(A:A) -> 2005 | K7: =MONTH(Table1[[#This Row],[Date]]) -> 1 | L7: =DAY(Table1[[#This Row],[Date]]) -> 12 | M7: =CHOOSE(K7,"Jan", "Feb", "Mar", "Apr", "May", "Jun", "Jul", "Aug", "Sep", "Oct", "Nov", "Dec") -> Jan
A8: 38736 | B8: Dammam | C8: Yahia | D8: Lulu | E8: Office | F8: 4896.58 | G8: 7880.54 | H8: =Table1[[#This Row],[Sale]]-Table1[[#This Row],[Cost]] -> 2983.96 | I8: =Table1[[#This Row],[Profit]]/Table1[[#This Row],[Sale]] -> 0.37864918 | J8: =YEAR(A:A) -> 2006 | K8: =MONTH(Table1[[#This Row],[Date]]) -> 1 | L8: =DAY(Table1[[#This Row],[Date]]) -> 19 | M8: =CHOOSE(K8,"Jan", "Feb", "Mar", "Apr", "May", "Jun", "Jul", "Aug", "Sep", "Oct", "Nov", "Dec") -> Jan
A9: 38272 | B9: Hail | C9: Yahia | D9: Othaim | E9: Toys | F9: 7133.74 | G9: 9511.66 | H9: =Table1[[#This Row],[Sale]]-Table1[[#This Row],[Cost]] -> 2377.92 | I9: =Table1[[#This Row],[Profit]]/Table1[[#This Row],[Sale]] -> 0.25000053 | J9: =YEAR(A:A) -> 2004 | K9: =MONTH(Table1[[#This Row],[Date]]) -> 10 | L9: =DAY(Table1[[#This Row],[Date]]) -> 12 | M9: =CHOOSE(K9,"Jan", "Feb", "Mar", "Apr", "May", "Jun", "Jul", "Aug", "Sep", "Oct", "Nov", "Dec") -> Oct
A10: 38426 | B10: Dammam | C10: Maliha | D10: Carrefour | E10: Food | F10: 3491.87 | G10: 8120.63 | H10: =Table1[[#This Row],[Sale]]-Table1[[#This Row],[Cost]] -> 4628.76 | I10: =Table1[[#This Row],[Profit]]/Table1[[#This Row],[Sale]] -> 0.57000011 | J10: =YEAR(A:A) -> 2005 | K10: =MONTH(Table1[[#This Row],[Date]]) -> 3 | L10: =DAY(Table1[[#This Row],[Date]]) -> 15 | M10: =CHOOSE(K10,"Jan", "Feb", "Mar", "Apr", "May", "Jun", "Jul", "Aug", "Sep", "Oct", "Nov", "Dec") -> Mar
A11: 38765 | B11: Jeddah | C11: Yahia | D11: Lulu | E11: Office | F11: 1350.06 | G11: 3000.14 | H11: =Table1[[#This Row],[Sale]]-Table1[[#This Row],[Cost]] -> 1650.08 | I11: =Table1[[#This Row],[Profit]]/Table1[[#This Row],[Sale]] -> 0.550001 | J11: =YEAR(A:A) -> 2006 | K11: =MONTH(Table1[[#This Row],[Date]]) -> 2 | L11: =DAY(Table1[[#This Row],[Date]]) -> 17 | M11: =CHOOSE(K11,"Jan", "Feb", "Mar", "Apr", "May", "Jun", "Jul", "Aug", "Sep", "Oct", "Nov", "Dec") -> Feb
A12: 38700 | B12: Jubail | C12: Yahia | D12: Carrefour | E12: Food | F12: 947.64 | G12: 2203.81 | H12: =Table1[[#This Row],[Sale]]-Table1[[#This Row],[Cost]] -> 1256.17 | I12: =Table1[[#This Row],[Profit]]/Table1[[#This Row],[Sale]] -> 0.56999923 | J12: =YEAR(A:A) -> 2005 | K12: =MONTH(Table1[[#This Row],[Date]]) -> 12 | L12: =DAY(Table1[[#This Row],[Date]]) -> 14 | M12: =CHOOSE(K12,"Jan", "Feb", "Mar", "Apr", "May", "Jun", "Jul", "Aug", "Sep", "Oct", "Nov", "Dec") -> Dec
A13: 38275 | B13: Jeddah | C13: Ghalia | D13: Panda | E13: Home | F13: 2648.96 | G13: 3531.95 | H13: =Table1[[#This Row],[Sale]]-Table1[[#This Row],[Cost]] -> 882.99 | I13: =Table1[[#This Row],[Profit]]/Table1[[#This Row],[Sale]] -> 0.25000071 | J13: =YEAR(A:A) -> 2004 | K13: =MONTH(Table1[[#This Row],[Date]]) -> 10 | L13: =DAY(Table1[[#This Row],[Date]]) -> 15 | M13: =CHOOSE(K13,"Jan", "Feb", "Mar", "Apr", "May", "Jun", "Jul", "Aug", "Sep", "Oct", "Nov", "Dec") -> Oct
... A1999: 38222 | B1999: Hail | C1999: Abdul | D1999: Carrefour | E1999: Office | F1999: 3081.97 | G1999: 3296.22 | H1999: =Table1[[#This Row],[Sale]]-Table1[[#This Row],[Cost]] -> 214.25 | I1999: =Table1[[#This Row],[Profit]]/Table1[[#This Row],[Sale]] -> 0.064998695 | J1999: =YEAR(A:A) -> 2004 | K1999: =MONTH(Table1[[#This Row],[Date]]) -> 8 | L1999: =DAY(Table1[[#This Row],[Date]]) -> 23 | M1999: =CHOOSE(K1999,"Jan", "Feb", "Mar", "Apr", "May", "Jun", "Jul", "Aug", "Sep", "Oct", "Nov", "Dec") -> Aug

Sheet Summary Analysis
L1: Basic Descriptive Statistics
A2: City Summary | F2: Sales Rep Summary | L2: Metric | M2: Sales Stat | N2: Profit Stat
A3: Row Labels | B3: Sum of Sale | C3: Sum of Profit | D3: Average of Margin % | F3: Row Labels | G3: Sum of Sale | H3: Sum of Profit | L3: count | M3: =COUNT('Clean Dataset'!G:G) -> 1998 | N3: =COUNT('Clean Dataset'!H:H) -> 1998
A4: Abha | B4: 1644938.7 | C4: 589363.57 | D4: 0.35001605 | F4: Abdul | G4: 1824241.9 | H4: 667750.67 | L4: mean | M4: =AVERAGE('Clean Dataset'!G:G) -> 5042.7232 | N4: =AVERAGE('Clean Dataset'!H:H) -> 1891.7029
A5: Dammam | B5: 1880961.3 | C5: 691918.64 | D5: 0.36449324 | F5: Ghalia | G5: 2107132.7 | H5: 814239.24 | L5: std | M5: =_xlfn.STDEV.S('Clean Dataset'!G:G) -> 2875.5892 | N5: =_xlfn.STDEV.S('Clean Dataset'!H:H) -> 1533.2078
A6: Hail | B6: 1481391.4 | C6: 552446.46 | D6: 0.37329541 | F6: Maliha | G6: 2088024.5 | H6: 763067.47 | L6: min | M6: =MIN('Clean Dataset'!G:G) -> 12.56 | N6: =MIN('Clean Dataset'!H:H) -> -2657.14
A7: Jeddah | B7: 1708310.2 | C7: 620362.91 | D7: 0.33566091 | F7: Mjeed | G7: 1878038.6 | H7: 700455.87 | L7: max | M7: =MAX('Clean Dataset'!G:G) -> 9994.24 | N7: =MAX('Clean Dataset'!H:H) -> 6292.79
A8: Jubail | B8: 1562105.6 | C8: 613097.38 | D8: 0.3834375 | F8: Yahia | G8: 2177923.2 | H8: 834109.06 | L8: SUM | M8: =SUM('Clean Dataset'!G:G) -> 10075361 | N8: =SUM('Clean Dataset'!H:H) -> 3779622.3
A9: Riyadh | B9: 1797653.7 | C9: 712433.35 | D9: 0.39505819 | F9: Grand Total | G9: 10075361 | H9: 3779622.3
A10: Grand Total | B10: 10075361 | C10: 3779622.3 | D10: 0.36650951
A11: Store Summary | F11: Product Category Summary | K11: Row Labels | L11: Sum of Sale
A12: Row Labels | B12: Sum of Sale | C12: Sum of Profit | D12: Sum of Margin % | F12: Row Labels | G12: Sum of Sale | H12: Sum of Profit | K12: 2004 | L12: 2756653
A13: Carrefour | B13: 2624334.2 | C13: 963309.33 | D13: 182.5801 | F13: Food | G13: 2692005.6 | H13: 1014215.4 | K13: Jun | L13: 213704.72
A14: Lulu | B14: 2477499.4 | C14: 931800.94 | D14: 186.4335 | F14: Home | G14: 2314318.7 | H14: 861158.84 | K14: Jul | L14: 402246.4
A15: Othaim | B15: 2462270.4 | C15: 922053.4 | D15: 181.3989 | F15: Office | G15: 2623694.2 | H15: 999289.56 | K15: Aug | L15: 438473.77
A16: Panda | B16: 2511257 | C16: 962458.64 | D16: 181.8735 | F16: Toys | G16: 2445342.4 | H16: 904958.5 | K16: Sep | L16: 449849.06
A17: Grand Total | B17: 10075361 | C17: 3779622.3 | D17: 732.286 | F17: Grand Total | G17: 10075361 | H17: 3779622.3 | K17: Oct | L17: 435078.36
K18: Nov | L18: 323764.41
K19: Dec | L19: 493536.23
K20: 2005 | L20: 5085395.9
K21: Jan | L21: 493478.79
K22: Feb | L22: 397159.58
K23: Mar | L23: 421915.84
K24: Apr | L24: 352684.06
K25: May | L25: 395194.85
K26: Jun | L26: 369263.03
K27: Jul | L27: 501652.39
K28: Aug | L28: 419055.66
K29: Sep | L29: 453661.01
K30: Oct | L30: 423459.3
K31: Nov | L31: 371671.08
K32: Dec | L32: 486200.34
K33: 2006 | L33: 2233312.1
K34: Jan | L34: 393883.33
K35: Feb | L35: 323847.96
K36: Mar | L36: 431754.94
K37: Apr | L37: 381416.99
K38: May | L38: 493488.57
K39: Jun | L39: 208920.31
K40: Grand Total | L40: 10075361

Sheet Dashboard
A1: Sales Performance Dashboard
